opyv/__init__.py
opyv/opyv.py
opyv-0.1.1.dist-info/LICENSE
opyv-0.1.1.dist-info/WHEEL
opyv-0.1.1.dist-info/METADATA
opyv-0.1.1.dist-info/RECORD
